{"id":"bb510fdb-5eee-4030-abbd-88a1b3ee9a92","profileKey":204,"version":0,"name":"MyProfile_12345","orgId":"65yV1dx1QpJlUikNRYACCR","description":null,"frsId":"8F5vbDWFYYWfa5LORRanKQ","frsProjectId":"5BABQgKDhfoeooda5Jxs0D","connectionId":"4KkVUmcw1owinNcfa3bquP","createdBy":"15lmvdJmSifbX77ru9bSgP","createdByName":"cpTest_git","createTime":1656930792572,"updatedBy":"15lmvdJmSifbX77ru9bSgP","updatedByName":"cpTest_git","updateTime":1656930792592,"isFilterEnabled":false,"runtimeOptions":{"id":"35de9eb7-6a50-4b5e-92d6-1868ef03e4b4","scheduleId":null,"runtimeEnvironmentId":null,"defaultEmailNotification":true,"profileAdvProps":{"maxTopN":null,"maxPatterns":null,"maxPatternThresholdPercent":null,"maxRanks":null,"inferDateTime":true,"detectOutliers":true,"enableClaireAnomalyDetection":null,"maxColumnsPerMapping":null,"minNoOfRowsForSplitMapping":null,"maxMemory":null,"maxPercentMemory":null,"defaultBufferBlockSize":null,"dtmBufferSize":null,"lineSequentialBufferLength":null,"stopOnErrors":null}},"source":{"id":"536ea0f0-bfc1-4367-9393-aa49a8cb0ac4","name":"CP_ALL_SUPPORTED_DATATYPE","fields":[{"id":"0441e4c3-61e9-4487-a3a3-318a248cf94d","name":"NUMERIC_COL","dataType":"decimal","precision":38,"scale":0,"pcType":"HIPRECDECIMAL","order":9,"isDeleted":false,"isMetadataUpdated":false},{"id":"10e2d2f5-c530-4f58-bce7-1638a9bcdc54","name":"DEC_COL","dataType":"decimal","precision":38,"scale":0,"pcType":"HIPRECDECIMAL","order":27,"isDeleted":false,"isMetadataUpdated":false},{"id":"af968896-fa65-431a-a709-2c88388be079","name":"CHARACTER_COL","dataType":"char","precision":1,"scale":0,"pcType":"STRING","order":31,"isDeleted":false,"isMetadataUpdated":false},{"id":"8f51c134-4c20-433c-878c-c55c2a2efaeb","name":"ROWID_COL","dataType":"varchar","precision":18,"scale":0,"pcType":"STRING","order":6,"isDeleted":false,"isMetadataUpdated":false},{"id":"3c89eeb1-19f2-44bc-a598-184231905b4d","name":"UROWID_COL","dataType":"varchar","precision":4000,"scale":0,"pcType":"STRING","order":1,"isDeleted":false,"isMetadataUpdated":false},{"id":"7e516b72-d860-4a2b-823b-be0a0800a031","name":"TIMESTAMPWITHLOCALTIMEZONE_COL","dataType":"timestamp","precision":23,"scale":3,"pcType":"DATE","order":4,"isDeleted":false,"isMetadataUpdated":false},{"id":"ecb06c05-d60c-4bfe-b5b5-cdd3163167d0","name":"NCHAR_COL","dataType":"nchar","precision":2,"scale":0,"pcType":"UNISTRING","order":13,"isDeleted":false,"isMetadataUpdated":false},{"id":"a19404b4-fccd-4f21-bd5c-2a9e515b286d","name":"NVARCHAR2_COL","dataType":"nvarchar","precision":40,"scale":0,"pcType":"UNISTRING","order":8,"isDeleted":false,"isMetadataUpdated":false},{"id":"efdf5cfe-7af9-40a5-9438-84e6b94e02a3","name":"SMALLINT_COL","dataType":"decimal","precision":38,"scale":0,"pcType":"HIPRECDECIMAL","order":5,"isDeleted":false,"isMetadataUpdated":false},{"id":"e9f3acb0-be1d-43d7-bf8d-be5ab951cb0f","name":"NATIONALCHAR_COL","dataType":"nchar","precision":2,"scale":0,"pcType":"UNISTRING","order":17,"isDeleted":false,"isMetadataUpdated":false},{"id":"616b777d-1fd0-45f5-bbea-8ed5cbce383a","name":"LONGVARCHAR_COL","dataType":"text","precision":32000,"scale":0,"pcType":"STRING","order":18,"isDeleted":false,"isMetadataUpdated":false},{"id":"b5315d37-77cd-4f94-b299-0bdc47801fed","name":"INTERVALDAYTOSECOND_COL","dataType":"varchar","precision":255,"scale":0,"pcType":"STRING","order":21,"isDeleted":false,"isMetadataUpdated":false},{"id":"eee125b2-5f07-4a51-befc-4f5cab0ab76a","name":"DECIMAL_COL","dataType":"decimal","precision":38,"scale":0,"pcType":"HIPRECDECIMAL","order":26,"isDeleted":false,"isMetadataUpdated":false},{"id":"4f897721-ed64-461c-8453-4b77bf7a6eeb","name":"CHARVARYING_COL","dataType":"varchar","precision":20,"scale":0,"pcType":"STRING","order":32,"isDeleted":false,"isMetadataUpdated":false},{"id":"7926c94c-c2de-4c7c-ae2c-e6eb7b899dc0","name":"CLOB_COL","dataType":"text","precision":32000,"scale":0,"pcType":"STRING","order":29,"isDeleted":false,"isMetadataUpdated":false},{"id":"2edafed0-a3a4-45a5-801b-bc3101b03daa","name":"CHARACTERVARYING_COL","dataType":"varchar","precision":20,"scale":0,"pcType":"STRING","order":30,"isDeleted":false,"isMetadataUpdated":false},{"id":"73a5cb7a-f6ed-415f-8c11-8df1dd368294","name":"REAL_COL","dataType":"double","precision":15,"scale":0,"pcType":"FLOAT","order":7,"isDeleted":false,"isMetadataUpdated":false},{"id":"caba64b2-7463-42e0-9fff-8bd669e8e06d","name":"INTERVALYEARTOMONTH_COL","dataType":"varchar","precision":255,"scale":0,"pcType":"STRING","order":20,"isDeleted":false,"isMetadataUpdated":false},{"id":"91cd5ed1-1161-488d-a680-9656244c31f5","name":"NUMBER_COL","dataType":"double","precision":15,"scale":0,"pcType":"FLOAT","order":10,"isDeleted":false,"isMetadataUpdated":false},{"id":"1dc234ac-ace0-4c97-a524-cfea413249f1","name":"TIMESTAMPWITHTIMEZONE_COL","dataType":"varchar","precision":33,"scale":0,"pcType":"STRING","order":3,"isDeleted":false,"isMetadataUpdated":false},{"id":"be80ef7f-239d-45f2-9484-ce0b15f80196","name":"LONG_COL_LONGNOTACCEPTING","dataType":"decimal","precision":38,"scale":0,"pcType":"HIPRECDECIMAL","order":19,"isDeleted":false,"isMetadataUpdated":false},{"id":"60602564-e5ab-48a6-bb22-fdbbb5a9eaf0","name":"INTEGER_COL","dataType":"decimal","precision":38,"scale":0,"pcType":"HIPRECDECIMAL","order":22,"isDeleted":false,"isMetadataUpdated":false},{"id":"d6b98380-e3f1-4b78-8e5c-1f1d6a45cafd","name":"BINARY_DOUBLE_COL","dataType":"double","precision":15,"scale":0,"pcType":"FLOAT","order":35,"isDeleted":false,"isMetadataUpdated":false},{"id":"053a5f98-71d8-4088-9c6e-21119aa5525e","name":"TIMESTAMP_COL","dataType":"timestamp","precision":23,"scale":3,"pcType":"DATE","order":2,"isDeleted":false,"isMetadataUpdated":false},{"id":"33292074-4333-4a49-a61d-9179e1de14a8","name":"FLOAT_COL","dataType":"double","precision":15,"scale":0,"pcType":"FLOAT","order":24,"isDeleted":false,"isMetadataUpdated":false},{"id":"5a368818-1560-4f74-a21c-aafefe52282d","name":"NCLOB_COL","dataType":"ntext","precision":32000,"scale":0,"pcType":"UNISTRING","order":11,"isDeleted":false,"isMetadataUpdated":false},{"id":"03c5b5d6-0def-4314-9590-665746b91b9a","name":"BINARY_FLOAT_COL","dataType":"real","precision":7,"scale":0,"pcType":"FLOAT","order":34,"isDeleted":false,"isMetadataUpdated":false},{"id":"3f04c19a-7546-4d15-83c2-71eece5aae99","name":"NATIONALCHARACTER_COL","dataType":"nchar","precision":2,"scale":0,"pcType":"UNISTRING","order":15,"isDeleted":false,"isMetadataUpdated":false},{"id":"41e93600-3ed6-4eef-bfe6-a85fccd0bf08","name":"CHAR_COL","dataType":"char","precision":1,"scale":0,"pcType":"STRING","order":33,"isDeleted":false,"isMetadataUpdated":false},{"id":"be4f0410-771c-4929-b719-a9155483b08b","name":"NCHARVARYING_COL","dataType":"nvarchar","precision":40,"scale":0,"pcType":"UNISTRING","order":12,"isDeleted":false,"isMetadataUpdated":false},{"id":"0604b2bd-ec26-474f-a56a-3826ec291d48","name":"NATIONALCHARACTERVARYING_COL","dataType":"nvarchar","precision":40,"scale":0,"pcType":"UNISTRING","order":14,"isDeleted":false,"isMetadataUpdated":false},{"id":"ab56e086-9ab0-4493-9945-a319dc3b7eba","name":"VARCHAR2_COL","dataType":"varchar","precision":20,"scale":0,"pcType":"STRING","order":0,"isDeleted":false,"isMetadataUpdated":false},{"id":"40195610-673e-44bd-813b-15dea09fa7c3","name":"DOUBLEPRECISION_COL","dataType":"double","precision":15,"scale":0,"pcType":"FLOAT","order":25,"isDeleted":false,"isMetadataUpdated":false},{"id":"ccf93613-f428-4136-93e7-eaec5e921a25","name":"DATE_COL","dataType":"timestamp","precision":23,"scale":3,"pcType":"DATE","order":28,"isDeleted":false,"isMetadataUpdated":false},{"id":"a0ce02e7-5b5c-48e7-a6e1-815753ecd5ae","name":"INT_COL","dataType":"decimal","precision":38,"scale":0,"pcType":"HIPRECDECIMAL","order":23,"isDeleted":false,"isMetadataUpdated":false},{"id":"2d5df1e1-0a80-49bd-8b41-a4dbf9c70026","name":"NATIONALCHARVARYING_COL","dataType":"nvarchar","precision":40,"scale":0,"pcType":"UNISTRING","order":16,"isDeleted":false,"isMetadataUpdated":false}],"dataSourceType":"ORACLE","properties":{"dataSourceType":"ORACLE"},"sourceType":"DATASOURCE"},"profileableFields":[{"id":"8524e09b-0c9c-477c-9a22-996ea4b7be35","isDeleted":false,"appliedBy":"USER","columnKey":10001,"sourceName":"CP_ALL_SUPPORTED_DATATYPE","fieldName":"VARCHAR2_COL","fieldType":"DATASOURCEFIELD"}],"samplingOptions":{"id":null,"rows":-1,"samplingType":"ALL_ROWS"},"drillDownType":"ON"}