{"id":"8678a1f0-c4ce-45ee-9718-5c5d79c1f1b9","profileKey":578,"version":0,"name":"Profile_checkIn_32533","orgId":"65yV1dx1QpJlUikNRYACCR","description":"Creating profile using Automation.","frsId":"e9H8moZJUEGcjgnTa6bfgV","connectionId":"4KkVUmcw1owinNcfa3bquP","createdBy":"jvlA54ympSUdFPImKNVIES","createdByName":"shalini_git","createTime":1657622227686,"updatedBy":"jvlA54ympSUdFPImKNVIES","updatedByName":"shalini_git","updateTime":1657622227688,"isFilterEnabled":null,"runtimeOptions":{"id":"99f93652-0a6a-4638-8f32-c96aad6f4688","scheduleId":null,"runtimeEnvironmentId":null,"defaultEmailNotification":true},"source":{"id":"dfbff2b2-5452-4cf2-82aa-24886d2123e6","name":"EMPLOYEES","fields":[{"id":"f90918c3-4960-4cce-8e2a-ea0e21243d8d","name":"TSWLTZ_COL9","dataType":"timestamp","precision":23,"scale":3,"pcType":"DATE","order":35,"isDeleted":false,"isMetadataUpdated":false},{"id":"c4bbbde0-0c88-4609-ad5f-e7d231a84369","name":"COL_NVARCHAR2","dataType":"nvarchar","precision":800,"scale":0,"pcType":"UNISTRING","order":23,"isDeleted":false,"isMetadataUpdated":false},{"id":"e12cd69c-6d5c-4926-94e5-26313104e73b","name":"BLANK_STR","dataType":"varchar","precision":10,"scale":0,"pcType":"STRING","order":40,"isDeleted":false,"isMetadataUpdated":false},{"id":"de5fa0a7-c084-4b8b-9327-16da2b8ea527","name":"COL_RAW","dataType":"varbinary","precision":20,"scale":0,"pcType":"BINARY","order":26,"isDeleted":false,"isMetadataUpdated":false},{"id":"0e13382c-1635-4962-a888-947c8b970c2f","name":"COL_BLOB","dataType":"longvarbinary","precision":32000,"scale":0,"pcType":"BINARY","order":27,"isDeleted":false,"isMetadataUpdated":false},{"id":"d459329b-6be6-46dd-80d6-7fcf9dc5c598","name":"TSWLTZ_COL","dataType":"timestamp","precision":23,"scale":3,"pcType":"DATE","order":33,"isDeleted":false,"isMetadataUpdated":false},{"id":"c638d946-67d3-456b-abe3-8a38e1276f1c","name":"COL_CLOB","dataType":"text","precision":32000,"scale":0,"pcType":"STRING","order":28,"isDeleted":false,"isMetadataUpdated":false},{"id":"9f8f7861-6513-415a-920f-86f40ec2bcc3","name":"MANAGER_ID","dataType":"decimal","precision":6,"scale":0,"pcType":"HIPRECDECIMAL","order":9,"isDeleted":false,"isMetadataUpdated":false},{"id":"de045a7f-101a-4b08-8c1c-afaecc39d18d","name":"COL_NUM38","dataType":"decimal","precision":38,"scale":0,"pcType":"HIPRECDECIMAL","order":13,"isDeleted":false,"isMetadataUpdated":false},{"id":"8057ae70-deed-4954-aee3-89df9b51e720","name":"COL_NUM19_2","dataType":"decimal","precision":19,"scale":2,"pcType":"HIPRECDECIMAL","order":15,"isDeleted":false,"isMetadataUpdated":false},{"id":"2d768215-3591-4da2-b099-270699a14daf","name":"COL_NUM28","dataType":"decimal","precision":28,"scale":0,"pcType":"HIPRECDECIMAL","order":18,"isDeleted":false,"isMetadataUpdated":false},{"id":"a2ae95b1-129b-4879-aee3-313049d23f9c","name":"XML_DATA","dataType":"text","precision":32000,"scale":0,"pcType":"STRING","order":36,"isDeleted":false,"isMetadataUpdated":false},{"id":"10660578-a6d5-4cec-857f-2d18f34f8681","name":"COL_VARCHAR255","dataType":"varchar","precision":255,"scale":0,"pcType":"STRING","order":19,"isDeleted":false,"isMetadataUpdated":false},{"id":"e215e981-aa46-4648-80b7-6c113292d838","name":"NULLCOL","dataType":"varchar","precision":100,"scale":0,"pcType":"STRING","order":11,"isDeleted":false,"isMetadataUpdated":false},{"id":"1e220d2d-4a83-48ff-8de9-2894fbbaed8e","name":"HIRE_DATE","dataType":"timestamp","precision":23,"scale":3,"pcType":"DATE","order":5,"isDeleted":false,"isMetadataUpdated":false},{"id":"9f5d0700-bfd5-487d-a6b0-538a58f5b546","name":"COL_TIMESTAMP","dataType":"timestamp","precision":23,"scale":3,"pcType":"DATE","order":22,"isDeleted":false,"isMetadataUpdated":false},{"id":"3a9b11bc-799b-4b12-8973-36e01b4e6674","name":"DEPARTMENT_ID","dataType":"decimal","precision":4,"scale":0,"pcType":"HIPRECDECIMAL","order":10,"isDeleted":false,"isMetadataUpdated":false},{"id":"a5fa8adc-2fdc-44b8-a0b7-68b7f8623995","name":"TSWTZ_COL","dataType":"varchar","precision":26,"scale":0,"pcType":"STRING","order":32,"isDeleted":false,"isMetadataUpdated":false},{"id":"b734ed3d-ebff-424f-9ab1-77da2e52d094","name":"COL_VARCHAR256","dataType":"varchar","precision":256,"scale":0,"pcType":"STRING","order":20,"isDeleted":false,"isMetadataUpdated":false},{"id":"168d8f5f-aa43-484d-b6c3-a0bcde594ba0","name":"EMPLOYEE_ID","dataType":"decimal","precision":6,"scale":0,"pcType":"HIPRECDECIMAL","order":0,"isDeleted":false,"isMetadataUpdated":false},{"id":"7582bf40-32b5-4f48-886f-c1083259d2e1","name":"COL_NUM38_38","dataType":"decimal","precision":38,"scale":38,"pcType":"HIPRECDECIMAL","order":12,"isDeleted":false,"isMetadataUpdated":false},{"id":"0e15ffb5-747d-4d09-91ed-8e38b35b34f3","name":"CAPS_NULL","dataType":"varchar","precision":20,"scale":0,"pcType":"STRING","order":37,"isDeleted":false,"isMetadataUpdated":false},{"id":"a17795a6-8e62-47fa-b7fa-90034e12bdf0","name":"LOWER_NULL","dataType":"varchar","precision":20,"scale":0,"pcType":"STRING","order":39,"isDeleted":false,"isMetadataUpdated":false},{"id":"99544ef1-faff-44af-8c73-8321a87ea67d","name":"INITCAPS_NULL","dataType":"varchar","precision":20,"scale":0,"pcType":"STRING","order":38,"isDeleted":false,"isMetadataUpdated":false},{"id":"575ca89d-d0a4-4337-bcc3-16af0eb99eff","name":"SALARY","dataType":"decimal","precision":8,"scale":2,"pcType":"HIPRECDECIMAL","order":7,"isDeleted":false,"isMetadataUpdated":false},{"id":"05c42a7c-8d50-46f0-96ad-42330fcdba9a","name":"LAST_NAME","dataType":"varchar","precision":25,"scale":0,"pcType":"STRING","order":2,"isDeleted":false,"isMetadataUpdated":false},{"id":"f2e36b04-37de-4fa9-b26d-9421b46822a0","name":"COL_DOUBLE","dataType":"double","precision":15,"scale":0,"pcType":"FLOAT","order":31,"isDeleted":false,"isMetadataUpdated":false},{"id":"2a613b24-1752-4b50-944f-b06084c6b41f","name":"COL_FLOAT","dataType":"double","precision":15,"scale":0,"pcType":"FLOAT","order":30,"isDeleted":false,"isMetadataUpdated":false},{"id":"45e167ee-b370-447c-9b6d-20d171503bfb","name":"PHONE_NUMBER","dataType":"varchar","precision":20,"scale":0,"pcType":"STRING","order":4,"isDeleted":false,"isMetadataUpdated":false},{"id":"6e77f76a-5a02-40cc-b34e-6725516cc523","name":"COL_LONG","dataType":"text","precision":32000,"scale":0,"pcType":"STRING","order":25,"isDeleted":false,"isMetadataUpdated":false},{"id":"db8a342b-8de0-43c0-abad-1c3cb7c51e26","name":"COL_NUM15","dataType":"decimal","precision":16,"scale":0,"pcType":"HIPRECDECIMAL","order":17,"isDeleted":false,"isMetadataUpdated":false},{"id":"c439ec58-1e00-4c9a-9ee7-68230b45091a","name":"COL_NUM38_2","dataType":"decimal","precision":38,"scale":2,"pcType":"HIPRECDECIMAL","order":14,"isDeleted":false,"isMetadataUpdated":false},{"id":"ea3edd4e-72f1-4287-bc16-3a0a8a8dcea5","name":"COL_NCHAR","dataType":"nchar","precision":304,"scale":0,"pcType":"UNISTRING","order":24,"isDeleted":false,"isMetadataUpdated":false},{"id":"3fe4af05-4766-43b0-a96e-be6709422c4e","name":"COMMISSION_PCT","dataType":"decimal","precision":3,"scale":2,"pcType":"HIPRECDECIMAL","order":8,"isDeleted":false,"isMetadataUpdated":false},{"id":"b884f877-bc82-4ecf-94a4-677b09930f23","name":"COL_NCLOB","dataType":"ntext","precision":32000,"scale":0,"pcType":"UNISTRING","order":29,"isDeleted":false,"isMetadataUpdated":false},{"id":"40926c3c-cbab-41e8-bbed-c91da4f392b5","name":"FIRST_NAME","dataType":"varchar","precision":20,"scale":0,"pcType":"STRING","order":1,"isDeleted":false,"isMetadataUpdated":false},{"id":"8c8f2124-d410-4e92-a04d-d740e279dd60","name":"COL_NUM19","dataType":"decimal","precision":19,"scale":0,"pcType":"HIPRECDECIMAL","order":16,"isDeleted":false,"isMetadataUpdated":false},{"id":"31471d83-cc2a-4f3f-8dd0-f4cb130bdaac","name":"EMAIL","dataType":"varchar","precision":25,"scale":0,"pcType":"STRING","order":3,"isDeleted":false,"isMetadataUpdated":false},{"id":"d2834712-2d24-4c80-8116-7301a4be13b8","name":"JOB_ID","dataType":"varchar","precision":10,"scale":0,"pcType":"STRING","order":6,"isDeleted":false,"isMetadataUpdated":false},{"id":"f45d48b8-f075-4680-a139-7233c8d3ffb1","name":"TSWTZ_COL9","dataType":"varchar","precision":26,"scale":0,"pcType":"STRING","order":34,"isDeleted":false,"isMetadataUpdated":false},{"id":"8f82295d-2c41-4077-bd36-66b874566cbf","name":"COL_VARCHAR254","dataType":"varchar","precision":254,"scale":0,"pcType":"STRING","order":21,"isDeleted":false,"isMetadataUpdated":false}],"dataSourceType":"UNSET","sourceType":"DATASOURCE"},"profileableFields":[{"id":"917c0e1c-d621-4992-be2b-34f1a215777c","isDeleted":false,"columnKey":10001,"sourceName":"EMPLOYEES","fieldName":"FIRST_NAME","fieldType":"DATASOURCEFIELD"}],"samplingOptions":{"id":null,"rows":-1,"samplingType":"ALL_ROWS"},"drillDownType":"ON"}