{
  "objectInfo" : {
    "id" : "9Kk1dmPcb9ZcY1twcjZOQi",
    "name" : "Git_Profile3045235",
    "type" : "PROFILE",
    "metadata" : {
      "modelVersion" : {
        "major" : 1,
        "minor" : 0
      },
      "repoInfo" : {
        "repoHandle" : "a4b01f56-ce8b-4f95-b472-6970e837a74f"
      },
      "contextAttributes" : [ ],
      "additionalInfo" : {
        "description" : "",
        "contentType" : "json",
        "documentState" : "VALID"
      }
    }
  },
  "dataFileExtension" : "json",
  "objectRefs" : [ {
    "id" : "9GLj6BQ5VcEez80sQt3s46",
    "name" : "Demo_Rule",
    "type" : "RULE_SPECIFICATION",
    "metadata" : {
      "modelVersion" : {
        "major" : 1,
        "minor" : 0
      },
      "repoInfo" : {
        "repoHandle" : "9GLj6BQ5VcEez80sQt3s46"
      },
      "contextAttributes" : null,
      "additionalInfo" : {
        "description" : "single input rule",
        "contentType" : "Binary",
        "documentState" : "VALID"
      }
    },
    "path" : "/Explore/Default"
  }, {
    "id" : "4KkVUmcw1owinNcfa3bquP",
    "name" : "ORA_SRC",
    "type" : "Connection",
    "metadata" : {
      "modelVersion" : {
        "major" : 0,
        "minor" : 0
      },
      "repoInfo" : {
        "repoHandle" : "0148R40B000000000002"
      },
      "contextAttributes" : null,
      "additionalInfo" : {
        "description" : null,
        "contentType" : "JSON",
        "documentState" : "COMPLETE"
      }
    },
    "path" : "/SYS"
  } ]
}